{
    "1friend_filenames": [
        "", 
        "", 
        "", 
        "", 
        "", 
        "", 
        "trainings/LongZCorrectedRecoil.root"
    ], 
    "1friend_treenames": [
        "", 
        "", 
        "", 
        "", 
        "", 
        "", 
        "LongZCorrectedRecoil"
    ], 
    "analysis_modules": [
        "ProjectByFit", 
        "Ratio"
    ], 
    "colors": [
        "navy", 
        "#003300", 
        "#005500", 
        "#006600", 
        "#007700", 
        "#008800", 
        "#009900", 
        "#00AA00", 
        "#00BB00", 
        "#00CC00", 
        "#003300", 
        "#005500", 
        "#006600", 
        "#007700", 
        "#008800", 
        "#009900", 
        "#00AA00", 
        "#00BB00", 
        "#00CC00"
    ], 
    "directories": [
        "/nfs/dust/cms/user/rfriese/puppet/scan/PUPPETAnalysis/"
    ], 
    "filename": "transverse_resolution_pt", 
    "files": [
        "DYJetsToLL_M-50_TuneCUETP8M1_13TeV-amcatnloFXFX-pythia8_Asympt50ns_MCRUN2_74_V9A_noMuon_JEC_ptFw_0p0.root", 
        "DYJetsToLL_M-50_TuneCUETP8M1_13TeV-amcatnloFXFX-pythia8_Asympt50ns_MCRUN2_74_V9A_noMuon_JEC_ptFw_0p0.root", 
        "DYJetsToLL_M-50_TuneCUETP8M1_13TeV-amcatnloFXFX-pythia8_Asympt50ns_MCRUN2_74_V9A_noMuon_JEC_ptFw_1p0.root", 
        "DYJetsToLL_M-50_TuneCUETP8M1_13TeV-amcatnloFXFX-pythia8_Asympt50ns_MCRUN2_74_V9A_noMuon_JEC_ptFw_1p5.root", 
        "DYJetsToLL_M-50_TuneCUETP8M1_13TeV-amcatnloFXFX-pythia8_Asympt50ns_MCRUN2_74_V9A_noMuon_JEC_ptFw_2p0.root", 
        "DYJetsToLL_M-50_TuneCUETP8M1_13TeV-amcatnloFXFX-pythia8_Asympt50ns_MCRUN2_74_V9A_noMuon_JEC_ptFw_2p5.root", 
        "DYJetsToLL_M-50_TuneCUETP8M1_13TeV-amcatnloFXFX-pythia8_Asympt50ns_MCRUN2_74_V9A_noMuon_JEC_ptFw_3p0.root", 
        "DYJetsToLL_M-50_TuneCUETP8M1_13TeV-amcatnloFXFX-pythia8_Asympt50ns_MCRUN2_74_V9A_noMuon_JEC_ptFw_3p5.root", 
        "DYJetsToLL_M-50_TuneCUETP8M1_13TeV-amcatnloFXFX-pythia8_Asympt50ns_MCRUN2_74_V9A_noMuon_JEC_ptFw_4p0.root", 
        "DYJetsToLL_M-50_TuneCUETP8M1_13TeV-amcatnloFXFX-pythia8_Asympt50ns_MCRUN2_74_V9A_noMuon_JEC_ptFw_5p0.root"
    ], 
    "fit_backend": [
        "ROOT"
    ], 
    "folders": [
        "PUPPET/t"
    ], 
    "grid": true, 
    "labels": [
        "PF", 
        "0.0", 
        "1.0", 
        "1.5", 
        "2.0", 
        "2.5", 
        "3.0", 
        "3.5", 
        "4.0", 
        "5.0"
    ], 
    "legend_cols": 3, 
    "line_styles": [
        "-"
    ], 
    "markers": [
        "."
    ], 
    "output_dir": "studies/study5", 
    "projection_function": [
        "gaus"
    ], 
    "projection_parameters": [
        "1000,10,10"
    ], 
    "projection_to_nick": [
        "nick0", 
        "nick1", 
        "nick2", 
        "nick3", 
        "nick4", 
        "nick5", 
        "nick6", 
        "nick7", 
        "nick8", 
        "nick9"
    ], 
    "projection_to_plot": [
        "2"
    ], 
    "ratio_denominator_nicks": [
        "nick0"
    ], 
    "ratio_numerator_nicks": [
        "nick1", 
        "nick2", 
        "nick3", 
        "nick4", 
        "nick5", 
        "nick6", 
        "nick7", 
        "nick8", 
        "nick9"
    ], 
    "subplot_fraction": 30, 
    "subplot_grid": true, 
    "weights": [
        "Boson_daughter==13"
    ], 
    "x_bins": [
        "10,0,200"
    ], 
    "x_errors": [
        false
    ], 
    "x_expressions": [
        "Boson_Pt"
    ], 
    "x_label": "$p_T^Z$", 
    "y_bins": [
        "50,-100,100"
    ], 
    "y_errors": [
        false
    ], 
    "y_expressions": [
        "recoilPFMet_PerpZ", 
        "recoilPFPuppiMet_PerpZ", 
        "recoilPFPuppiMet_PerpZ", 
        "recoilPFPuppiMet_PerpZ", 
        "recoilPFPuppiMet_PerpZ", 
        "recoilPFPuppiMet_PerpZ", 
        "recoilPFPuppiMet_PerpZ", 
        "recoilPFPuppiMet_PerpZ", 
        "recoilPFPuppiMet_PerpZ", 
        "recoilPFPuppiMet_PerpZ"
    ], 
    "y_label": "Resolution [GeV]", 
    "y_lims": [
        0, 
        40
    ]
}