{
    "analysis_modules": [
        "ProjectionY", 
        "FunctionPlot"
    ], 
    "filename": "Longitudinal_Response_controlplot_PF_Projection", 
    "files": [
        "root://eoscms.cern.ch//store/user/rgerosa/PUPPETAnalysis/DYJetsToLL_M-50_TuneCUETP8M1_13TeV-amcatnloFXFX-pythia8_Asympt50ns_MCRUN2_74_V9A_fixed.root"
    ], 
    "folders": [
        "PUPPET/t"
    ], 
    "function_fit": [
        "nick0_slice_0", 
        "nick0_slice_1", 
        "nick0_slice_2"
    ], 
    "function_parameters": [
        "1,1,1"
    ], 
    "functions": [
        "gaus"
    ], 
    "labels": [
        "PF"
    ], 
    "line_styles": [
        "", 
        "", 
        "", 
        "-", 
        "-", 
        "-"
    ], 
    "markers": [
        "."
    ], 
    "weights": [
        "Boson_daughter==13"
    ], 
    "x_bins": [
        "3,40,70"
    ], 
    "x_errors": [
        false
    ], 
    "x_expressions": [
        "Boson_Pt"
    ], 
    "y_bins": [
        "100,-4,6"
    ], 
    "y_errors": [
        false
    ], 
    "y_expressions": [
        "recoilPFMet_LongZ/-Boson_Pt"
    ]
}